{
    "GNN_hyperparameters":
    {
        "num_layers": 4,
        "hidden_channels": 32,
        "out_channels": 32,
        "hidden_edges": 4,
        "hidden_nodes": 4,
        "learning_rate": 5e-3,
        "warmup_height": 1.0,
        "warmup_ratio": 0.1,
        "minimum_lr_ratio": 0.05,
        "weight_decay": 1e-2,
        "num_epochs": 550,
        "batch_sizes": [64, 64, 64],
        "is_early_stopping": false
    },

    "Physical_hyperparameters":
    {   
        "Ls": ["4x4","5x5","6x6"], 
        "datasets": {"training": 0.8, "validation": 0.1, "test": 0.1},
        "train_realizations": 2000,
        "train_num_deltas": 10,
        "load_former_models": false,
        "incl_scnd": false,
        "trgt_diff": true
    },

    "Test_hyperparameters":
    {   
        "datasets": {"test": 1.0},
        "test_path": "../data-gen/Datasets/dataset_NO_Dr_X_Mg_NN_NNN_delta_one/test-fig4",
        "load_former_models": true,
        "test_Ls": ["4x4","5x5", "6x6", "7x6", "7x7", "8x7","8x8", "9x8", "9x9"],
        "test_realizations": 200,
        "test_num_deltas": 10
    },

    "General_parameters":
    {
        "save_to_one_shots": true,
        "save_variances": false,
        "folder_models": "./Results/models/",
        "folder_datasets": "../data-gen/Datasets/dataset_NO_Dr_X_Mg_NN_NNN_delta_one"
    }
}